<?xml version="1.0"?>
<savegame>
	<input />
	<window />
	<textures />
	<audio>
		<master_volume value="0" />
	</audio>
	<fonts />
	<gui />
	<map>
		<curr_map source="0" />
	</map>
	<pathfinding />
	<collisions />
	<entities>
		<entity type="0" entity_id="0">
			<speed x="0" y="0" />
			<position x="1414" y="452" />
			<state type="0" />
			<flip value="false" />
			<collision_box offset_x="" offset_y="" w="40" h="60" />
			<acceleration x="1" y="0.800000012" />
			<jump_force value="-18" />
			<max_speed x="8" y="16" />
			<render_scale value="1" />
			<life value="3" />
		</entity>
		<entity type="1" entity_id="0">
			<speed x="2" y="1" />
			<position x="1255" y="982" />
			<state type="1" />
			<flip value="false" />
			<collision_box offset_x="" offset_y="" w="30" h="30" />
			<acceleration x="0" y="0.5" />
			<jump_force value="-12" />
			<max_speed x="2" y="1" />
			<render_scale value="2" />
		</entity>
		<entity type="3" entity_id="0">
			<speed x="1.41421354" y="0" />
			<position x="1415" y="51" />
			<state type="1" />
			<flip value="false" />
			<collision_box offset_x="" offset_y="" w="30" h="30" />
			<acceleration x="0" y="0" />
			<jump_force value="0" />
			<max_speed x="1" y="1" />
			<render_scale value="2" />
		</entity>
		<entity type="3" entity_id="1">
			<speed x="1.41421354" y="0" />
			<position x="2246" y="57" />
			<state type="1" />
			<flip value="false" />
			<collision_box offset_x="" offset_y="" w="30" h="30" />
			<acceleration x="0" y="0" />
			<jump_force value="0" />
			<max_speed x="1" y="1" />
			<render_scale value="2" />
		</entity>
		<entity type="3" entity_id="2">
			<speed x="1.41421354" y="0" />
			<position x="2933" y="57" />
			<state type="1" />
			<flip value="false" />
			<collision_box offset_x="" offset_y="" w="30" h="30" />
			<acceleration x="0" y="0" />
			<jump_force value="0" />
			<max_speed x="1" y="1" />
			<render_scale value="2" />
		</entity>
		<entity type="1" entity_id="1">
			<speed x="2" y="1" />
			<position x="2395" y="757" />
			<state type="1" />
			<flip value="false" />
			<collision_box offset_x="" offset_y="" w="30" h="30" />
			<acceleration x="0" y="0.5" />
			<jump_force value="-12" />
			<max_speed x="2" y="1" />
			<render_scale value="2" />
		</entity>
		<entity type="1" entity_id="2">
			<speed x="2" y="1" />
			<position x="3698" y="737" />
			<state type="1" />
			<flip value="false" />
			<collision_box offset_x="" offset_y="" w="30" h="30" />
			<acceleration x="0" y="0.5" />
			<jump_force value="-12" />
			<max_speed x="2" y="1" />
			<render_scale value="2" />
		</entity>
		<entity type="3" entity_id="3">
			<speed x="1.41421354" y="0" />
			<position x="4230" y="296" />
			<state type="1" />
			<flip value="false" />
			<collision_box offset_x="" offset_y="" w="30" h="30" />
			<acceleration x="0" y="0" />
			<jump_force value="0" />
			<max_speed x="1" y="1" />
			<render_scale value="2" />
		</entity>
		<entity type="3" entity_id="4">
			<speed x="1.41421354" y="0" />
			<position x="5467" y="157" />
			<state type="1" />
			<flip value="false" />
			<collision_box offset_x="" offset_y="" w="30" h="30" />
			<acceleration x="0" y="0" />
			<jump_force value="0" />
			<max_speed x="1" y="1" />
			<render_scale value="2" />
		</entity>
		<entity type="1" entity_id="3">
			<speed x="2" y="1" />
			<position x="5961" y="589" />
			<state type="1" />
			<flip value="false" />
			<collision_box offset_x="" offset_y="" w="30" h="30" />
			<acceleration x="0" y="0.5" />
			<jump_force value="-12" />
			<max_speed x="2" y="1" />
			<render_scale value="2" />
		</entity>
	</entities>
	<scene />
	<renderer>
		<camera x="-1114" y="-180" />
	</renderer>
</savegame>
